{
  "main": {
    "id": "5f1c8c9f459c8862",
    "type": "split",
    "children": [
      {
        "id": "4a2727ebe6ca625f",
        "type": "tabs",
        "children": [
          {
            "id": "7d8086002432a1d1",
            "type": "leaf",
            "state": {
              "type": "empty",
              "state": {},
              "icon": "lucide-file",
              "title": "Tab mới"
            }
          }
        ]
      }
    ],
    "direction": "vertical"
  },
  "left": {
    "id": "ffd1520f7a36f3cf",
    "type": "split",
    "children": [
      {
        "id": "8dc64b1f9b9f96ae",
        "type": "tabs",
        "children": [
          {
            "id": "1edc889b8f8c1ff3",
            "type": "leaf",
            "state": {
              "type": "file-explorer",
              "state": {
                "sortOrder": "alphabetical",
                "autoReveal": false
              },
              "icon": "lucide-folder-closed",
              "title": "Trình duyệt tệp"
            }
          },
          {
            "id": "11fc170294715057",
            "type": "leaf",
            "state": {
              "type": "search",
              "state": {
                "query": "",
                "matchingCase": false,
                "explainSearch": false,
                "collapseAll": false,
                "extraContext": false,
                "sortOrder": "alphabetical"
              },
              "icon": "lucide-search",
              "title": "Tìm kiếm"
            }
          },
          {
            "id": "0be3c59ee5e7c84f",
            "type": "leaf",
            "state": {
              "type": "bookmarks",
              "state": {},
              "icon": "lucide-bookmark",
              "title": "Đánh dấu"
            }
          }
        ]
      }
    ],
    "direction": "horizontal",
    "width": 293.5
  },
  "right": {
    "id": "fef15c42c46c132c",
    "type": "split",
    "children": [
      {
        "id": "bd09adac5778d2b8",
        "type": "tabs",
        "children": [
          {
            "id": "007bfe553e5f8eda",
            "type": "leaf",
            "state": {
              "type": "backlink",
              "state": {
                "file": "Front-end/TypeScript.md",
                "collapseAll": false,
                "extraContext": false,
                "sortOrder": "alphabetical",
                "showSearch": false,
                "searchQuery": "",
                "backlinkCollapsed": false,
                "unlinkedCollapsed": true
              },
              "icon": "links-coming-in",
              "title": "Liên kết đến của TypeScript"
            }
          },
          {
            "id": "076a0dc3104ce1b4",
            "type": "leaf",
            "state": {
              "type": "outgoing-link",
              "state": {
                "file": "Web/Back-end/Express JS/Giới thiệu & Cài đặt Express JS.md",
                "linksCollapsed": false,
                "unlinkedCollapsed": true
              },
              "icon": "links-going-out",
              "title": "Liên kết đi ra từ Giới thiệu & Cài đặt Express JS"
            }
          },
          {
            "id": "0faa40351e6c4c8a",
            "type": "leaf",
            "state": {
              "type": "tag",
              "state": {
                "sortOrder": "frequency",
                "useHierarchy": true,
                "showSearch": false,
                "searchQuery": ""
              },
              "icon": "lucide-tags",
              "title": "Tags"
            }
          },
          {
            "id": "373bd21cb27d45d5",
            "type": "leaf",
            "state": {
              "type": "outline",
              "state": {
                "file": "Web/Back-end/Express JS/Giới thiệu & Cài đặt Express JS.md",
                "followCursor": false,
                "showSearch": false,
                "searchQuery": ""
              },
              "icon": "lucide-list",
              "title": "Đề cương của Giới thiệu & Cài đặt Express JS"
            }
          }
        ],
        "currentTab": 3
      }
    ],
    "direction": "horizontal",
    "width": 200,
    "collapsed": true
  },
  "left-ribbon": {
    "hiddenItems": {
      "switcher:Mở bộ chuyển đổi nhanh": false,
      "graph:Mở xem biểu đồ": false,
      "canvas:Tạo bảng mới": false,
      "daily-notes:Mở ghi chú hôm nay": false,
      "templates:Chèn mẫu": false,
      "command-palette:Mở khay lệnh": false,
      "bases:Create new base": false
    }
  },
  "active": "1edc889b8f8c1ff3",
  "lastOpenFiles": [
    "Kiến thức đại cương/Cơ sở dữ liệu/SQL/1. Nhập môn Cơ sở dữ liệu quan hệ.md",
    "Data/Machine learning/1.1. Các khái niệm cơ bản trong machine learning.md",
    "Data/Cơ sở toán học của Machine learning/1. Đại số tuyến tính (Linear algebra) và Numpy.md",
    "Data/Cơ sở toán học của Machine learning/3. Xác suất và Thống kê.md",
    "Kiến thức đại cương/Cơ sở dữ liệu/3. Mô hình quan hệ.md",
    "1. Nhập môn DDL, DML, SQL.md",
    "Kiến thức đại cương/Cơ sở dữ liệu/1. Tổng quan về Dữ liệu & Cơ sở dữ liệu.md",
    "Kiến thức đại cương/Nhập môn mạng/2. Application layer.md",
    "Web/Back-end/Express JS.md",
    "Data/Machine learning/3.3. Bài toán phân cụm & Thuật toán K-mean clustering.md",
    "Data/Machine learning/3.2. Bài toán Linear regression.md",
    "Data/Cơ sở toán học của Machine learning/2. Giải tích ma trận.md",
    "Data/Machine learning/3.1. Thuật toán K-nearest neighbors (KNN).md",
    "Data/Machine learning/2.2 Overfitting.md",
    "Web/Back-end/0. RESTful API.md",
    "Kiến thức đại cương/Nhập môn Java SE (Core)/6. Generic.md",
    "Kiến thức đại cương/Nhập môn Java SE (Core)/5. Một số thư viện chuẩn của Java.md",
    "Kiến thức đại cương/Nhập môn Java SE (Core)/5.1. Java Collection Framework.md",
    "Kiến thức đại cương/Nhập môn Java SE (Core)/6.1. Annotation.md",
    "Kiến thức đại cương/Nhập môn Java SE (Core)/4. OOP nâng cao.md",
    "Kiến thức đại cương/Nhập môn Java SE (Core)/3. OOP cơ bản.md",
    "Kiến thức đại cương/Nhập môn Java SE (Core)/3.1. Java reflection.md",
    "Kiến thức đại cương/Nhập môn Java SE (Core)/7. Giới thiệu & Cài đặt Apache Maven.md",
    "Web/Front-end/Tailwind CSS & Flowbite.md",
    "Web/Front-end/Vite.md",
    "Web/Front-end/Node.js.md",
    "Web/Back-end/Express JS",
    "Chưa đặt tên.base",
    "Chưa đặt tên 1.base",
    "Cơ sở dữ liệu/SQL"
  ]
}